fincookie/__init__.py
fincookie/api.py
fincookie-0.3.7.dist-info/LICENSE
fincookie-0.3.7.dist-info/METADATA
fincookie-0.3.7.dist-info/WHEEL
fincookie-0.3.7.dist-info/top_level.txt
fincookie-0.3.7.dist-info/RECORD
